weebapi/__init__.py
weebapi/client.py
weebapi/data_objects.py
weebapi/errors.py
weebapi/image.py
weebapi/image_type.py
weebapi/img_gen.py
weebapi/preview.py
weebapi/request_lib.py
weebapi/router.py
weebapi/tag.py
weebapi-0.1.14b0.dist-info/METADATA
weebapi-0.1.14b0.dist-info/WHEEL
weebapi-0.1.14b0.dist-info/top_level.txt
weebapi-0.1.14b0.dist-info/RECORD
